README.md
setup.cfg
setup.py
Python_to_dict.egg-info/PKG-INFO
Python_to_dict.egg-info/SOURCES.txt
Python_to_dict.egg-info/dependency_links.txt
Python_to_dict.egg-info/requires.txt
Python_to_dict.egg-info/top_level.txt
pytodict/__init__.py
pytodict/core.py
pytodict/custom_serializer_base.py