Metadata-Version: 2.1
Name: Python-to-dict
Version: 0.3
Summary: Serialize python objects to a dict
Home-page: https://github.com/egeback/pytodict
Author: Marky Egebäck
Author-email: marky@egeback.se
License: UNKNOWN
Download-URL: https://github.com/egeback/pytodict
Platform: UNKNOWN
